[
  { "region_name": "Bronx", "state_name": "NY", "student_count_all_time": 221 },
  {
    "region_name": "Queens",
    "state_name": "NY",
    "student_count_all_time": 1280
  },
  {
    "region_name": "Manhattan",
    "state_name": "NY",
    "student_count_all_time": 2782
  },
  {
    "region_name": "Staten Island",
    "state_name": "NY",
    "student_count_all_time": 105
  },
  {
    "region_name": "Brooklyn",
    "state_name": "NY",
    "student_count_all_time": 2393,
    "regional_contact": "Gretchen Ostheimer\\nGretchen.Ostheimer@hofstra.edu\\n551-556-7353"
  },
  {
    "region_name": "Bergen",
    "state_name": "NJ",
    "student_count_all_time": 350,
    "regional_contact": "Vikas Churiwalla\\nvchuri@mac.com\\n973-457-8680"
  },
  {
    "region_name": "Essex",
    "state_name": "NJ",
    "student_count_all_time": 198,
    "regional_contact": "Vikas Churiwalla\\nvchuri@mac.com\\n973-457-8680"
  },
  {
    "region_name": "Hudson",
    "state_name": "NJ",
    "student_count_all_time": 420,
    "regional_contact": "Vikas Churiwalla\\nvchuri@mac.com\\n973-457-8680"
  },
  {
    "region_name": "Hunterdon",
    "state_name": "NJ",
    "student_count_all_time": 38,
    "regional_contact": "Vikas Churiwalla\\nvchuri@mac.com\\n973-457-8680"
  },
  {
    "region_name": "Mercer",
    "state_name": "NJ",
    "student_count_all_time": 145,
    "regional_contact": "Vikas Churiwalla\\nvchuri@mac.com\\n973-457-8680"
  },
  {
    "region_name": "Middlesex",
    "state_name": "NJ",
    "student_count_all_time": 467,
    "regional_contact": "Vikas Churiwalla\\nvchuri@mac.com\\n973-457-8680"
  },
  {
    "region_name": "Monmouth",
    "state_name": "NJ",
    "student_count_all_time": 142,
    "regional_contact": "Vikas Churiwalla\\nvchuri@mac.com\\n973-457-8680"
  },
  {
    "region_name": "Morris",
    "state_name": "NJ",
    "student_count_all_time": 211,
    "regional_contact": "Vikas Churiwalla\\nvchuri@mac.com\\n973-457-8680"
  },
  {
    "region_name": "Passaic",
    "state_name": "NJ",
    "student_count_all_time": 112,
    "regional_contact": "Vikas Churiwalla\\nvchuri@mac.com\\n973-457-8680"
  },
  {
    "region_name": "Somerset",
    "state_name": "NJ",
    "student_count_all_time": 197,
    "regional_contact": "Vikas Churiwalla\\nvchuri@mac.com\\n973-457-8680"
  },
  {
    "region_name": "Sussex",
    "state_name": "NJ",
    "student_count_all_time": 20,
    "regional_contact": "Vikas Churiwalla\\nvchuri@mac.com\\n973-457-8680"
  },
  {
    "region_name": "Union",
    "state_name": "NJ",
    "student_count_all_time": 95,
    "regional_contact": "Vikas Churiwalla\\nvchuri@mac.com\\n973-457-8680"
  },
  {
    "region_name": "Warren",
    "state_name": "NJ",
    "student_count_all_time": 16,
    "regional_contact": "Vikas Churiwalla\\nvchuri@mac.com\\n973-457-8680"
  }
]
